{
  "lastUpdated": "2026-01-14T05:38:24.885Z",
  "rates": [
    {
      "item": "Gold Hallmark",
      "unit": "Tola",
      "rate": "278000"
    },
    {
      "item": "Gold Tajabi",
      "unit": "Tola",
      "rate": "275200"
    },
    {
      "item": "Silver",
      "unit": "Tola",
      "rate": "5655"
    },
    {
      "item": "Gold Hallmark",
      "unit": "10 gram",
      "rate": "238340"
    },
    {
      "item": "Gold Tajabi",
      "unit": "10 gram",
      "rate": "235956.6"
    },
    {
      "item": "Silver",
      "unit": "10 gram",
      "rate": "4848.50"
    }
  ]
}