{
  "lastUpdated": "2025-12-18T06:50:29.671Z",
  "rates": [
    {
      "item": "Gold Hallmark",
      "unit": "Tola",
      "rate": "260400"
    },
    {
      "item": "Gold Tajabi",
      "unit": "Tola",
      "rate": "257800"
    },
    {
      "item": "Silver",
      "unit": "Tola",
      "rate": "4080"
    },
    {
      "item": "Gold Hallmark",
      "unit": "10 gram",
      "rate": "223250"
    },
    {
      "item": "Gold Tajabi",
      "unit": "10 gram",
      "rate": "221017.5"
    },
    {
      "item": "Silver",
      "unit": "10 gram",
      "rate": "3498"
    }
  ]
}